odoo/addons/spreadsheet_dashboard_oca/README.rst
odoo/addons/spreadsheet_dashboard_oca/__init__.py
odoo/addons/spreadsheet_dashboard_oca/__manifest__.py
odoo/addons/spreadsheet_dashboard_oca/data/spreadsheet_spreadsheet_import_mode.xml
odoo/addons/spreadsheet_dashboard_oca/i18n/es.po
odoo/addons/spreadsheet_dashboard_oca/i18n/fr.po
odoo/addons/spreadsheet_dashboard_oca/i18n/fr_FR.po
odoo/addons/spreadsheet_dashboard_oca/i18n/it.po
odoo/addons/spreadsheet_dashboard_oca/i18n/nl.po
odoo/addons/spreadsheet_dashboard_oca/i18n/pt.po
odoo/addons/spreadsheet_dashboard_oca/i18n/spreadsheet_dashboard_oca.pot
odoo/addons/spreadsheet_dashboard_oca/i18n/zh_CN.po
odoo/addons/spreadsheet_dashboard_oca/models/__init__.py
odoo/addons/spreadsheet_dashboard_oca/models/spreadsheet_dashboard.py
odoo/addons/spreadsheet_dashboard_oca/readme/CONTRIBUTORS.md
odoo/addons/spreadsheet_dashboard_oca/readme/DESCRIPTION.md
odoo/addons/spreadsheet_dashboard_oca/static/description/icon.png
odoo/addons/spreadsheet_dashboard_oca/static/description/index.html
odoo/addons/spreadsheet_dashboard_oca/views/spreadsheet_dashboard.xml
odoo/addons/spreadsheet_dashboard_oca/views/spreadsheet_dashboard_group_views.xml
odoo/addons/spreadsheet_dashboard_oca/wizards/__init__.py
odoo/addons/spreadsheet_dashboard_oca/wizards/spreadsheet_spreadsheet_import.py
odoo/addons/spreadsheet_dashboard_oca/wizards/spreadsheet_spreadsheet_import.xml
odoo_addon_spreadsheet_dashboard_oca-18.0.1.0.1.2.dist-info/METADATA
odoo_addon_spreadsheet_dashboard_oca-18.0.1.0.1.2.dist-info/WHEEL
odoo_addon_spreadsheet_dashboard_oca-18.0.1.0.1.2.dist-info/top_level.txt
odoo_addon_spreadsheet_dashboard_oca-18.0.1.0.1.2.dist-info/RECORD
