Metadata-Version: 2.1
Name: odoo-addon-spreadsheet_dashboard_oca
Version: 18.0.1.0.1.2
Requires-Python: >=3.10
Requires-Dist: odoo-addon-spreadsheet_oca==18.0.*
Requires-Dist: odoo==18.0.*
Summary: Use OCA Spreadsheets on dashboards configuration
Home-page: https://github.com/OCA/spreadsheet
License: AGPL-3
Author: CreuBlanca,Odoo Community Association (OCA)
Author-email: support@odoo-community.org
Classifier: Programming Language :: Python
Classifier: Framework :: Odoo
Classifier: Framework :: Odoo :: 18.0
Classifier: License :: OSI Approved :: GNU Affero General Public License v3
